gofuncyourself.py
gofuncyourself-0.1.0.dist-info/WHEEL
gofuncyourself-0.1.0.dist-info/METADATA
gofuncyourself-0.1.0.dist-info/RECORD
