Metadata-Version: 2.1
Name: gofuncyourself
Version: 0.1.0
Summary: Go-like error handling, but with a twist
Author: L3viathan
Author-email: git@l3vi.de
Requires-Python: >=3.8,<4.0
Classifier: Programming Language :: Python :: 3
Classifier: Programming Language :: Python :: 3.8
